{
    "chapter_file": "0054.txt",
    "heading": "◎聆听",
    "analysis": {
        "nature": "混合型方法章节——通用写作技巧（聆听/读好改差/在角色内写作）~50% + 麦基『关键问题清单』体系~40% + 轶事~10%。通用技巧部分为行业共识（medium），关键问题清单中的节拍/价值/转折点框架属于麦基特有体系（debatable），问题清单中的一般性问题（欲望对象/对抗力量来源）属通用创作原则（medium）。",
        "certainty": "mixed——medium主导（通用技巧+一般性问题）+ debatable（节拍/价值/四层次分析框架）",
        "media": "hybrid（章节跨媒介讨论对白技巧，包含电影/舞台/小说）",
        "bias_note": "本章为麦基《对白》中关于聆听与在角色内写作的方法论章节。『关键问题清单』中的节拍/价值/转折点框架属于麦基特有理论建构；『从外向内/从内向外』写作方式和在角色内写作(If魔法)则源自斯坦尼斯拉夫斯基表演体系，非麦基独创。"
    },
    "part_files_covered": ["text/part0103.html"]
}
