[
    {"_index": 1739, "applicable_media": ["hybrid"]},
    {"_index": 1740, "framework_bias_note": "本章为麦基《人物》书第十七章「卡司设计」。『太阳系卡司模型』（主人公/第一圈/第二圈/第三圈）属于麦基特有的人物关系分析框架。"},
    {"_index": 1744, "applicable_media": ["hybrid"]},
    {"_index": 1751, "applicable_media": ["hybrid"], "framework_bias_note": "本章为麦基《人物》书第十七章。角色关系中逆转与揭示的功能分析属于麦基特有框架。"},
    {"_index": 1763, "framework_bias_note": "本章为麦基《人物》书第十七章。卡司设计中激励事件对人物关系网的冲击分析属于麦基故事设计框架的延伸。"},
    {"_index": 1764, "framework_bias_note": "本章为麦基《人物》书第十七章。卡司阵容的平衡与失衡动力学属于麦基特有的人物关系分析框架。"},
    {"_index": 1768, "applicable_media": ["hybrid"], "framework_bias_note": "本章为麦基《人物》书第十七章。叙事三角（大情节/小情节/反情节）在卡司设计中的应用属于麦基故事三角理论的延伸。"},
    {"_index": 1769, "framework_bias_note": "本章为麦基《人物》书第十七章。人物关系中的转折点分析属于麦基特有分析框架。"},
    {"_index": 1770, "applicable_media": ["hybrid"]},
    {"_index": 1771, "applicable_media": ["hybrid"]},
    {"_index": 1772, "applicable_media": ["hybrid"]},
    {"_index": 1773, "applicable_media": ["hybrid"]},
    {"_index": 1774, "applicable_media": ["hybrid"]},
    {"_index": 1775, "applicable_media": ["hybrid"]},
    {"_index": 1776, "applicable_media": ["hybrid"]},
    {"_index": 1781, "applicable_media": ["hybrid"]},
    {"_index": 1788, "applicable_media": ["hybrid"]},
    {"_index": 1796, "applicable_media": ["hybrid"]},
    {"_index": 1801, "applicable_media": ["hybrid"]}
]
