[
  {"_index":215,"certainty":"debatable","applicable_media":["hybrid"],"framework_bias_note":"\"审美情感\"是麦基核心美学概念——思想与情感同步体验。属于麦基特有的理论建构。"},
  {"_index":216,"certainty":"debatable","applicable_media":["hybrid"],"framework_bias_note":"\"故事是非理性的\"是麦基的美学立场——通过感觉和知觉、直觉和情感交流，而非理性论述。"},
  {"_index":217,"certainty":"medium","applicable_media":["hybrid"],"framework_bias_note":"该主张基于麦基对\"理性与非理性联姻\"的理解——好故事既非纯理性也非纯情感。"},
  {"_index":218,"certainty":"debatable","applicable_media":["hybrid"],"framework_bias_note":"\"前提\"（开放性问题触发创作）是麦基对创作驱动的概念化。"},
  {"_index":219,"certainty":"medium","applicable_media":["hybrid"],"framework_bias_note":"\"魔术般的如果\"——斯坦尼斯拉夫斯基的方法，非麦基独有。通用创作触发技巧。"},
  {"_index":220,"certainty":"medium","applicable_media":["hybrid"],"framework_bias_note":"\"灵感可来自任何地方\"——跨框架共识的创作常识。"},
  {"_index":221,"certainty":"medium","applicable_media":["film"],"framework_bias_note":"麦基以伯格曼《假面》的创作起源为例说明灵感的非理性来源。"},
  {"_index":222,"certainty":"medium","applicable_media":["hybrid"],"framework_bias_note":"\"前提不一定要保留在作品中\"——跨框架共识的创作经验。"},
  {"_index":223,"certainty":"medium","applicable_media":["hybrid"],"framework_bias_note":"\"关键是继续写\"——跨框架共识的创作经验。"},
  {"_index":224,"certainty":"debatable","applicable_media":["hybrid"],"framework_bias_note":"\"主控思想\"是麦基理论的核心概念——通过故事高潮传达的终极意义。"},
  {"_index":225,"certainty":"debatable","applicable_media":["hybrid"],"framework_bias_note":"\"故事讲述是对真理的创造性论证\"——麦基对故事修辞功能的定义。属于其特有理论表述。"},
  {"_index":226,"certainty":"debatable","applicable_media":["hybrid"],"framework_bias_note":"\"故事大师从不解释\"是麦基的核心创作原则之一——强反对解释性对白。"},
  {"_index":227,"certainty":"medium","applicable_media":["hybrid"],"framework_bias_note":"\"伟大的故事仅凭事件动态设计来确证思想\"——麦基\"展示勿告诉\"原则的延伸。通用创作原理。"},
  {"_index":228,"certainty":"medium","applicable_media":["hybrid"],"framework_bias_note":"麦基以犯罪类型为例说明\"思想通过动作被表演出来\"。"},
  {"_index":229,"certainty":"medium","applicable_media":["hybrid"],"framework_bias_note":"\"故事的意义必须通过具有情感表现力的故事高潮来表达\"——跨框架共识的创作原则。"},
  {"_index":230,"certainty":"medium","applicable_media":["film"],"framework_bias_note":"该主张基于麦基对\"主控思想\"的进一步阐述——价值+原因双成分。属于其理论体系。"},
  {"_index":231,"certainty":"medium","applicable_media":["film"],"framework_bias_note":"同上——主控思想的价值成分举例。"},
  {"_index":232,"certainty":"medium","applicable_media":["film"],"framework_bias_note":"麦基以社会中不同价值选择的后果为例说明主控思想的原因成分。"},
  {"_index":233,"certainty":"debatable","applicable_media":["hybrid"],"framework_bias_note":"\"主控思想=价值+原因\"的公式是麦基的理论建构——将故事意义归纳为二元公式。"},
  {"_index":234,"certainty":"debatable","applicable_media":["hybrid"],"framework_bias_note":"\"主控思想是纯动作的结果，不能借用对白\"——麦基理论的核心要求。"},
  {"_index":235,"certainty":"debatable","applicable_media":["hybrid"],"framework_bias_note":"麦基以《温柔怜悯》和《荒谬三人行》为例对比说明主控思想如何通过行动表达。"},
  {"_index":236,"certainty":"medium","applicable_media":["film"],"framework_bias_note":"\"主控思想是故事最终的动作和观众情感\"——麦基的理论定义。"},
  {"_index":237,"certainty":"debatable","applicable_media":["hybrid"],"framework_bias_note":"\"主题\"与\"主控思想\"的区分是麦基理论的特有表述。"},
  {"_index":238,"certainty":"medium","applicable_media":["hybrid"],"framework_bias_note":"\"作者自己相信的思想才能打动观众\"——跨框架共识的创作原理。"},
  {"_index":239,"certainty":"medium","applicable_media":["hybrid"],"framework_bias_note":"\"观众通过背景观点镜头看世界\"——麦基的观众接受理论。"},
  {"_index":240,"certainty":"medium","applicable_media":["hybrid"],"framework_bias_note":"\"主控思想有各种类型\"——对积极/消极/讽刺等高控思想的分类。"},
  {"_index":241,"certainty":"medium","applicable_media":["film"],"framework_bias_note":"麦基以不同影片为例说明各种主控思想类型。"},
  {"_index":242,"certainty":"medium","applicable_media":["film"],"framework_bias_note":"同上——各类主控思想影片举例。"},
  {"_index":243,"certainty":"debatable","applicable_media":["film"],"framework_bias_note":"\"当代影片缺乏讽刺反讽\"是麦基的个人观察与批判。"},
  {"_index":244,"certainty":"debatable","applicable_media":["film"],"framework_bias_note":"\"作家对思想的处理分为三个步骤\"——麦基对创作过程的特有描述。"},
  {"_index":245,"certainty":"medium","applicable_media":["hybrid"],"framework_bias_note":"\"质问故事每一个节拍的意义\"——通用创作检验方法。"},
  {"_index":246,"certainty":"medium","applicable_media":["hybrid"],"framework_bias_note":"\"从前提→故事→主控思想的演变\"——麦基对創作过程的三段论描述。"},
  {"_index":247,"certainty":"medium","applicable_media":["hybrid"],"framework_bias_note":"\"若主控思想与前提不同也算成功\"——麦基对创作过程中思想演变的开放态度。"},
  {"_index":248,"certainty":"medium","applicable_media":["hybrid"],"framework_bias_note":"\"奥斯卡最佳影片并非有最深刻的思想\"——麦基对大奖作品的观察。"},
  {"_index":249,"certainty":"medium","applicable_media":["hybrid"],"framework_bias_note":"\"故事的艺术不是讲述人类生存的混乱\"——麦基对故事功能的哲学立场。"},
  {"_index":250,"certainty":"medium","applicable_media":["hybrid"],"framework_bias_note":"\"故事是生活的比喻，引导我们透过现象看到本质\"——麦基的核心创作哲学。"},
  {"_index":251,"certainty":"medium","applicable_media":["hybrid"],"framework_bias_note":"\"观众希望生活有意义\"——跨框架共识的基本人性假设。"},
  {"_index":252,"certainty":"debatable","applicable_media":["hybrid"],"framework_bias_note":"\"故事意义必须通过具有情感表现力的故事高潮戏剧化表达，不能借用解释性对白\"——麦基\"展示勿告诉\"原则的极致表述。"},
  {"_index":253,"certainty":"medium","applicable_media":["hybrid"],"framework_bias_note":"\"作者如果不相信自己的故事，观众也不会\"——通用创作原理。"},
  {"_index":254,"certainty":"medium","applicable_media":["hybrid"],"framework_bias_note":"该主张基于麦基\"故事的娱乐=体验故事的意义\"的定义。"},
  {"_index":255,"certainty":"medium","applicable_media":["hybrid"],"framework_bias_note":"该主张基于麦基对故事意义从\"意识形态\"到\"客观真实\"的追求。"},
  {"_index":256,"certainty":"debatable","applicable_media":["film"],"framework_bias_note":"\"故事产生的愉悦是一种双重感情\"——麦基对审美体验的独特分析。"},
  {"_index":257,"certainty":"medium","applicable_media":["film"],"framework_bias_note":"\"我们流泪时不是为自己\"——麦基对观众移情体验的描述。"},
  {"_index":258,"certainty":"medium","applicable_media":["film"],"framework_bias_note":"\"两种愉悦：发现和再发现\"——麦基对Lubitsch和Chaplin的对比分析。"},
  {"_index":259,"certainty":"medium","applicable_media":["film"],"framework_bias_note":"\"伟大的作家从不投降，无论遇到什么挑战\"——麦基对作家职业精神的阐述。"},
  {"_index":260,"certainty":"medium","applicable_media":["film"],"framework_bias_note":"\"观众离开影院后会忘记笑声和眼泪，但不会忘记思想\"——麦基对故事长期影响的看法。"},
  {"_index":261,"certainty":"medium","applicable_media":["hybrid"],"framework_bias_note":"\"思想使人获得力量\"——麦基对故事思想的实用主义看法。"},
  {"_index":262,"certainty":"medium","applicable_media":["film"],"framework_bias_note":"\"生活需要积极/消极/讽刺三者的平衡\"——麦基的人生哲学。"},
  {"_index":263,"certainty":"medium","applicable_media":["film"],"framework_bias_note":"\"思想体系在市场上有生命周期\"——麦基对观众接受度的实用观察。"},
  {"_index":264,"certainty":"medium","applicable_media":["film"],"framework_bias_note":"\"唯一的嘲弄是自嘲\"——麦基的创作伦理立场。"}
]
