[
  {"_index": 382, "framework_bias_note": "该主张基于麦基的进展纠葛理论，是鸿沟原理和冲突递增模型的核心定义。在散文式或氛围主导的叙事中冲突推进的方式可能不同。"},
  {"_index": 383, "framework_bias_note": "该主张基于麦基的鸿沟理论（The Gap），认为每一行动都会在期望与结果之间产生鸿沟。在不同叙事传统中冲突爆发的方式可能更加渐进。"},
  {"_index": 384, "applicable_media": ["hybrid"], "framework_bias_note": "该主张基于麦基的鸿沟理论（不归点概念）。适用于所有叙事媒介，但冲突递增模型在实验性叙事或氛围主导型作品中需灵活调整。"},
  {"_index": 385, "framework_bias_note": "该主张基于麦基的三阶段冲突递增模型。在实际创作中冲突升级的节奏和幅度因故事类型不同而差异很大。"},
  {"_index": 386, "framework_bias_note": "该主张基于麦基的鸿沟理论和冲突递增模型，认为冲突必须通过三个以上不归点逐级推进。在短篇或小情节叙事中不归点的数量可能减少。"},
  {"_index": 387, "applicable_media": ["hybrid"], "framework_bias_note": "该主张以电影观看体验为例说明故事中段拖沓问题，其核心原理（避免重复和退行）适用于所有叙事媒介。在小说中可通过章节节奏而非场景序列来体现。"},
  {"_index": 389, "framework_bias_note": "该主张是麦基冲突驱动叙事的核心理念。冲突法则在氛围主导、意识流或某些日常生活叙事中需宽泛解释。"},
  {"_index": 391, "applicable_media": ["hybrid"], "framework_bias_note": "该主张将冲突类比为故事的乐音，是跨媒介的普遍创作原理。具体到时间流逝的体验在不同媒介中表现形式不同。"},
  {"_index": 393, "applicable_media": ["hybrid"]},
  {"_index": 394, "applicable_media": ["hybrid"]},
  {"_index": 397, "applicable_media": ["hybrid"]},
  {"_index": 406, "framework_bias_note": "该主张基于麦基对冲突层面的三分法分类体系。肥皂剧作为类型存在多种变体，其冲突模式不限于个人冲突层面。"},
  {"_index": 408, "applicable_media": ["hybrid"]},
  {"_index": 412, "applicable_media": ["hybrid"]},
  {"_index": 415, "framework_bias_note": "该主张基于麦基独有的节拍-场景-序列-幕四级结构体系。其他叙事理论可能采用不同的层级划分。"},
  {"_index": 416, "framework_bias_note": "该主张引用亚里士多德的观点，但麦基对其进行了特定方向的引申。在实验性短篇作品中可不遵循该规律。"},
  {"_index": 418, "applicable_media": ["hybrid"], "framework_bias_note": "该主张基于麦基对两幕结构的界定，提及了情境喜剧、中篇小说和戏剧等媒介。实际创作中两幕结构存在更多变体。"},
  {"_index": 419, "applicable_media": ["hybrid"]},
  {"_index": 420, "applicable_media": ["hybrid"], "framework_bias_note": "该主张基于麦基对故事结构的特定理解，认为长篇叙事必须通过至少三个重大逆转推进。实际创作中存在小情节、反情节等变体，且逆转的定义因媒介而异。"},
  {"_index": 422, "framework_bias_note": "该主张基于经典好莱坞电影的幕结构比例，包含具体的时间量化（25%、20分钟等）。在电视剧、小说或实验电影中需大幅调整。"},
  {"_index": 423, "framework_bias_note": "该主张基于三幕结构中第二幕过长的问题，提出次情节和新增幕作为解决方案。在小说或短篇叙事中表现形式不同。"},
  {"_index": 424, "framework_bias_note": "该主张基于主情节驱动、次情节穿插的叙事模型。在多情节或编织式结构中不适用。"},
  {"_index": 425, "framework_bias_note": "该主张基于电影剧本写作的特定编排策略。在小说或电视剧中次情节的节奏控制方式不同。"},
  {"_index": 426, "framework_bias_note": "该主张基于电影媒介的特定需求。在小说中幕的分割方式通常更灵活，不依赖精确的时间比例。"},
  {"_index": 427, "framework_bias_note": "该主张基于三幕故事的标准化分析。实际创作中重大场景的数量和分布可以在很大范围内变化。"},
  {"_index": 429, "framework_bias_note": "该主张基于动作片类型的观察。在其他类型中幕高潮的价值负荷分布不同，重复风险也相应降低。"},
  {"_index": 431, "framework_bias_note": "该主张基于麦基对故事形态的数量化分类体系。故事类型的边界在实际创作中更加模糊，不能仅凭逆转数量判定。"},
  {"_index": 432, "framework_bias_note": "该主张基于主情节驱动叙事的框架。在多情节或群像式叙事中激励事件的定义和定位方式不同。"},
  {"_index": 433, "framework_bias_note": "该主张基于电影叙事的具体技术考量。在小说中角色的内心刻画可替代伏笔式次情节的部分功能。"},
  {"_index": 434, "framework_bias_note": "该主张基于电影节奏的具体量化讨论。不同媒介和风格对节奏的要求差异很大，不存在固定公式。"},
  {"_index": 435, "framework_bias_note": "该主张继续讨论激励事件和第一幕高潮之间的时序关系，基于好莱坞电影的具体实践。在其他叙事传统中节奏安排更为多样。"},
  {"_index": 436, "framework_bias_note": "该主张认为幕节奏取决于创作者、人物和世界观，本身是对结构决定论的反思，具有一定的普遍性。"},
  {"_index": 437, "framework_bias_note": "该主张基于动作片的类型惯例。在其他类型中假结尾的使用频率和效果差异很大。"},
  {"_index": 439, "framework_bias_note": "该主张基于希区柯克的特定创作实践，不属于普遍性创作原理。"},
  {"_index": 440, "framework_bias_note": "该主张反映麦基的个人偏好。在现代叙事中假结尾已被多种类型广泛使用。"},
  {"_index": 441, "applicable_media": ["hybrid"], "framework_bias_note": "该主张基于正面/负面价值交替的戏剧节奏原理。在反情节或非线性叙事中价值变化的模式可能更加复杂。"},
  {"_index": 442, "framework_bias_note": "该主张基于麦基对反讽结局的特定分析框架。在实际创作中反讽的倾斜度判断存在较大主观空间。"},
  {"_index": 443, "framework_bias_note": "该主张通过《奥塞罗》等经典案例分析反讽高潮，属于麦基的理论阐释。反讽的本质判定取决于读者/观众的具体解读。"},
  {"_index": 444, "framework_bias_note": "该主张描述了幕节奏的一般规律，各幕高潮的负荷方向存在多种变通可能而非严格固定。"},
  {"_index": 445, "applicable_media": ["hybrid"]},
  {"_index": 450, "framework_bias_note": "该主张基于麦基对多情节结构的系统化描述。多情节的组织方式比文中所述更为多样，中心串联物可以是人物、地点或主题。"},
  {"_index": 452, "framework_bias_note": "该主张基于主情节激励事件推迟时的特定需求。在非主情节驱动型故事中不适用。"},
  {"_index": 453, "framework_bias_note": "该主张基于好莱坞电影的具体案例分析。不同文化和媒介传统中对激励事件时机的处理差异很大。"},
  {"_index": 454, "applicable_media": ["hybrid"]},
  {"_index": 455, "applicable_media": ["hybrid"]},
  {"_index": 456, "framework_bias_note": "该主张基于电影中观众移情机制的特定假设。在小说或群像剧中次情节人物的移情管理方式不同。"},
  {"_index": 457, "applicable_media": ["hybrid"]},
  {"_index": 458, "applicable_media": ["hybrid"], "framework_bias_note": "该主张基于主情节和次情节必须存在结构性/主题性关联的前提。在碎片化或并置式叙事中这一前提不成立。"},
  {"_index": 464, "framework_bias_note": "该主张基于《蜘蛛女之吻》的特定案例分析，属于特例而非普遍原则。"}
]
